sutime/__init__.py
sutime/jars/stanford-corenlp-sutime-python-1.4.0.jar
sutime/pom.xml
sutime/sutime.py
sutime/test/conftest.py
sutime/test/test_sutime.py
sutime/test/test_sutime_jvm_flags.py
sutime/test/test_sutime_spanish.py
sutime/test/test_sutime_time_ranges.py
sutime-1.0.1.dist-info/LICENSE
sutime-1.0.1.dist-info/WHEEL
sutime-1.0.1.dist-info/METADATA
sutime-1.0.1.dist-info/RECORD
