Metadata-Version: 2.1
Name: sutime
Version: 1.0.1
Summary: A Python wrapper for Stanford CoreNLP's SUTime
Home-page: https://github.com/FraBle/python-sutime
License: GPL-3.0-or-later
Keywords: stanford,corenlp,sutime,datetime,nlp
Author: Frank Blechschmidt
Author-email: contact@frank-blechschmidt.com
Requires-Python: >=3.6,<4.0
Classifier: Development Status :: 5 - Production/Stable
Classifier: Intended Audience :: Developers
Classifier: License :: OSI Approved :: GNU General Public License v3 or later (GPLv3+)
Classifier: Programming Language :: Python :: 3
Classifier: Programming Language :: Python :: 3.6
Classifier: Programming Language :: Python :: 3.7
Classifier: Programming Language :: Python :: 3.8
Classifier: Programming Language :: Python :: 3.9
Classifier: Topic :: Scientific/Engineering :: Artificial Intelligence
Classifier: Topic :: Scientific/Engineering :: Human Machine Interfaces
Classifier: Topic :: Software Development :: Libraries
Classifier: Topic :: Text Processing :: Linguistic
Requires-Dist: JPype1 (>=1.1.2,<2.0.0)
Project-URL: Documentation, https://github.com/FraBle/python-sutime
Project-URL: Repository, https://github.com/FraBle/python-sutime
